flipdigit/__init__.py
flipdigit/flipdigit.py
flipdigit-0.1.0.dist-info/LICENSE
flipdigit-0.1.0.dist-info/METADATA
flipdigit-0.1.0.dist-info/WHEEL
flipdigit-0.1.0.dist-info/top_level.txt
flipdigit-0.1.0.dist-info/RECORD
