Metadata-Version: 2.1
Name: flipdigit
Version: 0.1.0
Summary: Small flip digit library
Home-page: https://github.com/lucblender/FlipDigitPython
Author: Lucas Bonvin
License: MIT
Platform: UNKNOWN
Classifier: Programming Language :: Python :: 3
Classifier: License :: OSI Approved :: MIT License
Classifier: Operating System :: OS Independent
Requires-Python: >=3.6
Requires-Dist: pyserial
